maguiclient/__init__.py
maguiclient/magui.py
maguiclient/remote.yml
maguiclient/hooks/data/0/fail-faraday.py
maguiclient/plugins/core/faraday-magui.py
maguiclient/plugins/core/metadata-outputs.py
maguiclient/plugins/core/risu-outputs.py
maguiclient/plugins/openstack/mysql/seqno.py
maguiclient/plugins/system/mtu.py
maguiclient/plugins/system/multipathluns.py
maguiclient/plugins/system/release.py
risu-1.14.4.20241216203926.data/scripts/citellus.py
risu-1.14.4.20241216203926.data/scripts/env-for-debug.sh
risu-1.14.4.20241216203926.data/scripts/magui.py
risu-1.14.4.20241216203926.data/scripts/risu.py
risuclient/__init__.py
risuclient/common-functions.sh
risuclient/magui.py
risuclient/risu.html
risuclient/risu.sh
risuclient/shell.py
risuclient/common.d/00-core.sh
risuclient/common.d/01-date.sh
risuclient/common.d/01-dpkg.sh
risuclient/common.d/01-rpm.sh
risuclient/common.d/01-virt.sh
risuclient/common.d/02-pkg.sh
risuclient/common.d/10-openshift.sh
risuclient/common.d/10-openstack.sh
risuclient/common.d/20-container.sh
risuclient/extensions/.placeholder
risuclient/extensions/__init__.py
risuclient/extensions/ansible.py
risuclient/extensions/core.py
risuclient/extensions/faraday-exec.py
risuclient/extensions/faraday.py
risuclient/extensions/golang.py
risuclient/extensions/metadata.py
risuclient/extensions/nagios.py
risuclient/extensions/node-problem-detector.py
risuclient/extensions/rhv-log-collector-analyzer.py
risuclient/extensions/tripleo-common-healthcheck.py
risuclient/extensions/winston.py
risuclient/hooks/data/0/faraday-exec/merge-with-faraday.py
risuclient/hooks/data/0/insights-core-unifier-merge-loader/insights-json.py
risuclient/hooks/data/0/network/move-global-mtu-to-individual-faraday-positive.py
risuclient/hooks/data/0/system/move-global-multipath-to-individual-faraday-positive.py
risuclient/hooks/data/9/faraday-to-individual.py
risuclient/hooks/data/9/rhv-log-collector-analyzer-to-individual.py
risuclient/hooks/data/9/system/unfail-chronyd-with-ntpd.py
risu-1.14.4.20241216203926.dist-info/LICENSE
risu-1.14.4.20241216203926.dist-info/METADATA
risu-1.14.4.20241216203926.dist-info/WHEEL
risu-1.14.4.20241216203926.dist-info/pbr.json
risu-1.14.4.20241216203926.dist-info/top_level.txt
risu-1.14.4.20241216203926.dist-info/RECORD
