Metadata-Version: 2.1
Name: risu
Version: 1.14.4.20241216203926
Summary: Utility for running set of tests against a Live System or a snapshot/sosreport
Home-page: https://github.com/risuorg/risu
Author: Robin Černín
Author-email: cerninr@gmail.com
License: GPL3
Classifier: Environment :: Console
Classifier: Environment :: OpenStack
Classifier: Intended Audience :: Customer Service
Classifier: Intended Audience :: Developers
Classifier: Intended Audience :: Information Technology
Classifier: Intended Audience :: System Administrators
Classifier: Intended Audience :: Telecommunications Industry
Classifier: License :: OSI Approved :: GNU General Public License v3 or later (GPLv3+)
Classifier: Operating System :: POSIX :: Linux
Classifier: Programming Language :: Python
Classifier: Programming Language :: Python :: 2
Classifier: Programming Language :: Python :: 2.7
Classifier: Programming Language :: Python :: 3
Classifier: Programming Language :: Python :: 3.5
Classifier: Programming Language :: Unix Shell
Classifier: Topic :: Security
Classifier: Topic :: System
Classifier: Topic :: Utilities
License-File: LICENSE
Requires-Dist: requests
Requires-Dist: urllib3>=2.2.2
Requires-Dist: zombie-imp
